{
    "Цистерна": {
        "dohod": 0,
        "loading_revenue": 0,
        "rent_revenue": 0,
        "penalties": 0,
        "rashod": 13805441.679999998,
        "peremen_rashod": 13771266.58,
        "tariff_rf": 13463960.0,
        "tariff_inroad": 0,
        "expedition": 307306.58,
        "prepare": 0,
        "pps": 0,
        "post_rashod": 34175.100000000006,
        "rent_expenses": 0,
        "repair": 0,
        "amortization": 34175.100000000006,
        "salary": 0,
        "other_expenses": 0,
        "oper_prib": -13805441.679999998
    },
    "dohod": 0,
    "loading_revenue": 0,
    "rent_revenue": 0,
    "penalties": 0,
    "rashod": 27567142.68,
    "peremen_rashod": 27532967.580000002,
    "tariff_rf": 27225661.0,
    "tariff_inroad": 0,
    "expedition": 307306.58,
    "prepare": 0,
    "pps": 0,
    "post_rashod": 34175.100000000006,
    "rent_expenses": 0,
    "repair": 0,
    "amortization": 34175.100000000006,
    "salary": 0,
    "other_expenses": 0,
    "oper_prib": -27567142.68,
    "Полувагон": {
        "dohod": 0,
        "loading_revenue": 0,
        "rent_revenue": 0,
        "penalties": 0,
        "rashod": 13761701.0,
        "peremen_rashod": 13761701.0,
        "tariff_rf": 13761701.0,
        "tariff_inroad": 0,
        "expedition": 0,
        "prepare": 0,
        "pps": 0,
        "post_rashod": 0,
        "rent_expenses": 0,
        "repair": 0,
        "amortization": 0,
        "salary": 0,
        "other_expenses": 0,
        "oper_prib": -13761701.0
    }
}